{
    "adapterID": "file:/Volumes/MNFirelight/firelight/packages/metanorma-site-content",
    "content": {
        "primaryLanguageID": "ja",
        "labelInPlainText": "4.21.3.1.1  gen:stringAttribute",
        "title": {
            "type": "doc",
            "content": [
                {
                    "type": "text",
                    "text": "4.21.3.1.1  gen:stringAttribute"
                }
            ]
        },
        "contentSchemaID": "clause",
        "contentDoc": {
            "type": "doc",
            "content": [
                {
                    "type": "title",
                    "content": [
                        {
                            "type": "text",
                            "text": "4.21.3.1.1  gen:stringAttribute"
                        }
                    ]
                },
                {
                    "type": "figure",
                    "attrs": {
                        "resourceID": "urn:metanorma-xml-id:_86381440-e5c6-c031-e282-eb50a482d762"
                    },
                    "content": [
                        {
                            "type": "figCaption",
                            "content": [
                                {
                                    "type": "text",
                                    "text": "表4-829"
                                }
                            ]
                        },
                        {
                            "type": "table",
                            "attrs": {
                                "colWidths": [
                                    "25%",
                                    "25%",
                                    "50%"
                                ]
                            },
                            "content": [
                                {
                                    "type": "table_row",
                                    "content": [
                                        {
                                            "type": "table_header",
                                            "attrs": {
                                                "colspan": null,
                                                "rowspan": null,
                                                "colwidth": null,
                                                "background": null
                                            },
                                            "content": [
                                                {
                                                    "type": "paragraph",
                                                    "attrs": {
                                                        "resourceID": ""
                                                    },
                                                    "content": [
                                                        {
                                                            "type": "text",
                                                            "text": "クラスの定義"
                                                        }
                                                    ]
                                                }
                                            ]
                                        },
                                        {
                                            "type": "table_header",
                                            "attrs": {
                                                "colspan": "2",
                                                "rowspan": null,
                                                "colwidth": null,
                                                "background": null
                                            },
                                            "content": [
                                                {
                                                    "type": "paragraph",
                                                    "attrs": {
                                                        "resourceID": ""
                                                    },
                                                    "content": [
                                                        {
                                                            "type": "text",
                                                            "text": "文字列型の汎用属性。CityGML又はi-URに定義されていない文字列型の属性を追加したい場合に使用する。"
                                                        }
                                                    ]
                                                }
                                            ]
                                        }
                                    ]
                                },
                                {
                                    "type": "table_row",
                                    "content": [
                                        {
                                            "type": "table_header",
                                            "attrs": {
                                                "colspan": null,
                                                "rowspan": null,
                                                "colwidth": null,
                                                "background": null
                                            },
                                            "content": [
                                                {
                                                    "type": "paragraph",
                                                    "attrs": {
                                                        "resourceID": ""
                                                    },
                                                    "content": [
                                                        {
                                                            "type": "text",
                                                            "text": "上位の型"
                                                        }
                                                    ]
                                                }
                                            ]
                                        },
                                        {
                                            "type": "table_cell",
                                            "attrs": {
                                                "colspan": "2",
                                                "rowspan": null,
                                                "colwidth": null,
                                                "background": null
                                            },
                                            "content": [
                                                {
                                                    "type": "paragraph",
                                                    "attrs": {
                                                        "resourceID": "urn:metanorma-xml-id:_8d670212-3d7d-1698-266f-600adcfaf433"
                                                    },
                                                    "content": [
                                                        {
                                                            "type": "text",
                                                            "text": "gen:_genericAttribute"
                                                        }
                                                    ]
                                                }
                                            ]
                                        }
                                    ]
                                },
                                {
                                    "type": "table_row",
                                    "content": [
                                        {
                                            "type": "table_header",
                                            "attrs": {
                                                "colspan": null,
                                                "rowspan": null,
                                                "colwidth": null,
                                                "background": null
                                            },
                                            "content": [
                                                {
                                                    "type": "paragraph",
                                                    "attrs": {
                                                        "resourceID": ""
                                                    },
                                                    "content": [
                                                        {
                                                            "type": "text",
                                                            "text": "ステレオタイプ"
                                                        }
                                                    ]
                                                }
                                            ]
                                        },
                                        {
                                            "type": "table_cell",
                                            "attrs": {
                                                "colspan": "2",
                                                "rowspan": null,
                                                "colwidth": null,
                                                "background": null
                                            },
                                            "content": [
                                                {
                                                    "type": "paragraph",
                                                    "attrs": {
                                                        "resourceID": "urn:metanorma-xml-id:_7ca0942b-2bfa-7d61-e551-077227e7fb3b"
                                                    },
                                                    "content": [
                                                        {
                                                            "type": "text",
                                                            "text": "<< DataType >>"
                                                        }
                                                    ]
                                                }
                                            ]
                                        }
                                    ]
                                },
                                {
                                    "type": "table_row",
                                    "content": [
                                        {
                                            "type": "table_header",
                                            "attrs": {
                                                "colspan": "3",
                                                "rowspan": null,
                                                "colwidth": null,
                                                "background": null
                                            },
                                            "content": [
                                                {
                                                    "type": "paragraph",
                                                    "attrs": {
                                                        "resourceID": ""
                                                    },
                                                    "content": [
                                                        {
                                                            "type": "text",
                                                            "text": "継承する属性"
                                                        }
                                                    ]
                                                }
                                            ]
                                        }
                                    ]
                                },
                                {
                                    "type": "table_row",
                                    "content": [
                                        {
                                            "type": "table_header",
                                            "attrs": {
                                                "colspan": null,
                                                "rowspan": null,
                                                "colwidth": null,
                                                "background": null
                                            },
                                            "content": [
                                                {
                                                    "type": "paragraph",
                                                    "attrs": {
                                                        "resourceID": ""
                                                    },
                                                    "content": [
                                                        {
                                                            "type": "text",
                                                            "text": "属性名"
                                                        }
                                                    ]
                                                }
                                            ]
                                        },
                                        {
                                            "type": "table_header",
                                            "attrs": {
                                                "colspan": null,
                                                "rowspan": null,
                                                "colwidth": null,
                                                "background": null
                                            },
                                            "content": [
                                                {
                                                    "type": "paragraph",
                                                    "attrs": {
                                                        "resourceID": ""
                                                    },
                                                    "content": [
                                                        {
                                                            "type": "text",
                                                            "text": "属性の型及び多重度"
                                                        }
                                                    ]
                                                }
                                            ]
                                        },
                                        {
                                            "type": "table_header",
                                            "attrs": {
                                                "colspan": null,
                                                "rowspan": null,
                                                "colwidth": null,
                                                "background": null
                                            },
                                            "content": [
                                                {
                                                    "type": "paragraph",
                                                    "attrs": {
                                                        "resourceID": ""
                                                    },
                                                    "content": [
                                                        {
                                                            "type": "text",
                                                            "text": "定義"
                                                        }
                                                    ]
                                                }
                                            ]
                                        }
                                    ]
                                },
                                {
                                    "type": "table_row",
                                    "content": [
                                        {
                                            "type": "table_cell",
                                            "attrs": {
                                                "colspan": null,
                                                "rowspan": null,
                                                "colwidth": null,
                                                "background": null
                                            },
                                            "content": [
                                                {
                                                    "type": "paragraph",
                                                    "attrs": {
                                                        "resourceID": "urn:metanorma-xml-id:_3421a355-7410-2dd0-53d9-925c7b440dcb"
                                                    },
                                                    "content": [
                                                        {
                                                            "type": "text",
                                                            "text": "gen:name"
                                                        }
                                                    ]
                                                }
                                            ]
                                        },
                                        {
                                            "type": "table_cell",
                                            "attrs": {
                                                "colspan": null,
                                                "rowspan": null,
                                                "colwidth": null,
                                                "background": null
                                            },
                                            "content": [
                                                {
                                                    "type": "paragraph",
                                                    "attrs": {
                                                        "resourceID": "urn:metanorma-xml-id:_dbd812ef-3bd5-5dc6-1109-b27697a4f0be"
                                                    },
                                                    "content": [
                                                        {
                                                            "type": "text",
                                                            "text": "xs:string [1]"
                                                        }
                                                    ]
                                                }
                                            ]
                                        },
                                        {
                                            "type": "table_cell",
                                            "attrs": {
                                                "colspan": null,
                                                "rowspan": null,
                                                "colwidth": null,
                                                "background": null
                                            },
                                            "content": [
                                                {
                                                    "type": "paragraph",
                                                    "attrs": {
                                                        "resourceID": "urn:metanorma-xml-id:_aa1510ae-9852-870d-cac3-4f0eb154e56f"
                                                    },
                                                    "content": [
                                                        {
                                                            "type": "text",
                                                            "text": "汎用属性の名称。"
                                                        }
                                                    ]
                                                }
                                            ]
                                        }
                                    ]
                                },
                                {
                                    "type": "table_row",
                                    "content": [
                                        {
                                            "type": "table_header",
                                            "attrs": {
                                                "colspan": "3",
                                                "rowspan": null,
                                                "colwidth": null,
                                                "background": null
                                            },
                                            "content": [
                                                {
                                                    "type": "paragraph",
                                                    "attrs": {
                                                        "resourceID": ""
                                                    },
                                                    "content": [
                                                        {
                                                            "type": "text",
                                                            "text": "自身に定義された属性"
                                                        }
                                                    ]
                                                }
                                            ]
                                        }
                                    ]
                                },
                                {
                                    "type": "table_row",
                                    "content": [
                                        {
                                            "type": "table_header",
                                            "attrs": {
                                                "colspan": null,
                                                "rowspan": null,
                                                "colwidth": null,
                                                "background": null
                                            },
                                            "content": [
                                                {
                                                    "type": "paragraph",
                                                    "attrs": {
                                                        "resourceID": ""
                                                    },
                                                    "content": [
                                                        {
                                                            "type": "text",
                                                            "text": "属性名"
                                                        }
                                                    ]
                                                }
                                            ]
                                        },
                                        {
                                            "type": "table_header",
                                            "attrs": {
                                                "colspan": null,
                                                "rowspan": null,
                                                "colwidth": null,
                                                "background": null
                                            },
                                            "content": [
                                                {
                                                    "type": "paragraph",
                                                    "attrs": {
                                                        "resourceID": ""
                                                    },
                                                    "content": [
                                                        {
                                                            "type": "text",
                                                            "text": "属性の型及び多重度"
                                                        }
                                                    ]
                                                }
                                            ]
                                        },
                                        {
                                            "type": "table_header",
                                            "attrs": {
                                                "colspan": null,
                                                "rowspan": null,
                                                "colwidth": null,
                                                "background": null
                                            },
                                            "content": [
                                                {
                                                    "type": "paragraph",
                                                    "attrs": {
                                                        "resourceID": ""
                                                    },
                                                    "content": [
                                                        {
                                                            "type": "text",
                                                            "text": "定義"
                                                        }
                                                    ]
                                                }
                                            ]
                                        }
                                    ]
                                },
                                {
                                    "type": "table_row",
                                    "content": [
                                        {
                                            "type": "table_cell",
                                            "attrs": {
                                                "colspan": null,
                                                "rowspan": null,
                                                "colwidth": null,
                                                "background": null
                                            },
                                            "content": [
                                                {
                                                    "type": "paragraph",
                                                    "attrs": {
                                                        "resourceID": "urn:metanorma-xml-id:_96c00b54-556c-7064-5b4f-d5f537f90b59"
                                                    },
                                                    "content": [
                                                        {
                                                            "type": "text",
                                                            "text": "gen:value"
                                                        }
                                                    ]
                                                }
                                            ]
                                        },
                                        {
                                            "type": "table_cell",
                                            "attrs": {
                                                "colspan": null,
                                                "rowspan": null,
                                                "colwidth": null,
                                                "background": null
                                            },
                                            "content": [
                                                {
                                                    "type": "paragraph",
                                                    "attrs": {
                                                        "resourceID": "urn:metanorma-xml-id:_013b0a8f-63bb-76b9-f0e8-4b5dcea4a6b2"
                                                    },
                                                    "content": [
                                                        {
                                                            "type": "text",
                                                            "text": "xs:string [1]"
                                                        }
                                                    ]
                                                }
                                            ]
                                        },
                                        {
                                            "type": "table_cell",
                                            "attrs": {
                                                "colspan": null,
                                                "rowspan": null,
                                                "colwidth": null,
                                                "background": null
                                            },
                                            "content": [
                                                {
                                                    "type": "paragraph",
                                                    "attrs": {
                                                        "resourceID": "urn:metanorma-xml-id:_522d0189-3263-1e59-3a21-16ab2a1c8b4a"
                                                    },
                                                    "content": [
                                                        {
                                                            "type": "text",
                                                            "text": "汎用属性の値。"
                                                        }
                                                    ]
                                                }
                                            ]
                                        }
                                    ]
                                }
                            ]
                        }
                    ]
                }
            ]
        }
    }
}